sshaolin/__init__.py
sshaolin/behaviors.py
sshaolin/client.py
sshaolin/common.py
sshaolin/models.py
sshaolin/proxy.py
sshaolin-0.0.6.dist-info/DESCRIPTION.rst
sshaolin-0.0.6.dist-info/METADATA
sshaolin-0.0.6.dist-info/RECORD
sshaolin-0.0.6.dist-info/WHEEL
sshaolin-0.0.6.dist-info/metadata.json
sshaolin-0.0.6.dist-info/top_level.txt
