Metadata-Version: 2.0
Name: sshaolin
Version: 0.0.6
Summary: SSH for Ninjas
Home-page: UNKNOWN
Author: Nathan Buckner
Author-email: bucknerns@gmail.com
License: Apache License
Requires-Dist: paramiko
Requires-Dist: pysocks
Requires-Dist: six
